mlscratch/__init__.py
mlscratch/datasets/__init__.py
mlscratch/datasets/load_data.py
mlscratch/supervised/__init__.py
mlscratch/supervised/decision_tree.py
mlscratch/supervised/elastic_net.py
mlscratch/supervised/gradient_boosting.py
mlscratch/supervised/knn.py
mlscratch/supervised/lasso_regression.py
mlscratch/supervised/linear_regression.py
mlscratch/supervised/logistic_regression.py
mlscratch/supervised/ridge_regression.py
mlscratch/supervised/simple_decision_tree.py
mlscratch/supervised/svm.py
mlscratch/supervised/svm_sgd.py
mlscratch/tests/__init__.py
mlscratch/tests/test_clustering.py
mlscratch/tests/test_decision_tree.py
mlscratch/tests/test_linear_regression.py
mlscratch/tests/test_logistic_regression.py
mlscratch/unsupervised/__init__.py
mlscratch/unsupervised/dbscan.py
mlscratch/unsupervised/hierarchical.py
mlscratch/unsupervised/kmeans.py
mlscratch/unsupervised/pca.py
mlscratch/unsupervised/svd.py
mlscratchlib-0.1.dist-info/licenses/LICENSE
mlscratchlib-0.1.dist-info/METADATA
mlscratchlib-0.1.dist-info/WHEEL
mlscratchlib-0.1.dist-info/top_level.txt
mlscratchlib-0.1.dist-info/RECORD
